sparrow_client/__init__.py
sparrow_client/sparrow_client.py
sparrow_client/core/__init__.py
sparrow_client/core/slack_command.py
sparrow_client/core/sparrow_exception.py
sparrow_client/core/sparrow_message.py
sparrow_client/core/queue/__init__.py
sparrow_client/core/queue/redis_queue.py
sparrow_client/core/queue/sparrow_client_queue.py
sparrow_client-1.0.7.dist-info/METADATA
sparrow_client-1.0.7.dist-info/WHEEL
sparrow_client-1.0.7.dist-info/top_level.txt
sparrow_client-1.0.7.dist-info/RECORD
