Metadata-Version: 2.1
Name: sparrow-client
Version: 1.0.7
Summary: sparrow_client
Home-page: UNKNOWN
Author: yeoseot
Author-email: changyeon@peoplefund.co.kr
License: UNKNOWN
Platform: UNKNOWN
Requires-Python: >=3.6
Requires-Dist: redis (>=3.3.8)
Requires-Dist: requests (>=2.22.0)
